ironic_lib/__init__.py
ironic_lib/auth_basic.py
ironic_lib/exception.py
ironic_lib/keystone.py
ironic_lib/mdns.py
ironic_lib/metrics.py
ironic_lib/metrics_collector.py
ironic_lib/metrics_statsd.py
ironic_lib/metrics_utils.py
ironic_lib/utils.py
ironic_lib/wsgi.py
ironic_lib/common/__init__.py
ironic_lib/common/config.py
ironic_lib/common/i18n.py
ironic_lib/json_rpc/__init__.py
ironic_lib/json_rpc/client.py
ironic_lib/json_rpc/server.py
ironic_lib/tests/__init__.py
ironic_lib/tests/base.py
ironic_lib/tests/test_base.py
ironic_lib/tests/test_basic_auth.py
ironic_lib/tests/test_exception.py
ironic_lib/tests/test_json_rpc.py
ironic_lib/tests/test_keystone.py
ironic_lib/tests/test_mdns.py
ironic_lib/tests/test_metrics.py
ironic_lib/tests/test_metrics_collector.py
ironic_lib/tests/test_metrics_statsd.py
ironic_lib/tests/test_metrics_utils.py
ironic_lib/tests/test_utils.py
ironic_lib-7.0.0.data/data/etc/ironic/rootwrap.d/ironic-lib.filters
ironic_lib-7.0.0.dist-info/AUTHORS
ironic_lib-7.0.0.dist-info/LICENSE
ironic_lib-7.0.0.dist-info/METADATA
ironic_lib-7.0.0.dist-info/WHEEL
ironic_lib-7.0.0.dist-info/entry_points.txt
ironic_lib-7.0.0.dist-info/pbr.json
ironic_lib-7.0.0.dist-info/top_level.txt
ironic_lib-7.0.0.dist-info/RECORD
