Metadata-Version: 2.1
Name: ironic-lib
Version: 7.0.0
Summary: Ironic common library
Home-page: https://docs.openstack.org/ironic-lib/
Author: OpenStack Ironic
Author-email: openstack-discuss@lists.openstack.org
License: UNKNOWN
Platform: UNKNOWN
Classifier: Environment :: OpenStack
Classifier: Intended Audience :: Information Technology
Classifier: Intended Audience :: System Administrators
Classifier: License :: OSI Approved :: Apache Software License
Classifier: Operating System :: POSIX :: Linux
Classifier: Programming Language :: Python
Classifier: Programming Language :: Python :: Implementation :: CPython
Classifier: Programming Language :: Python :: 3 :: Only
Classifier: Programming Language :: Python :: 3
Classifier: Programming Language :: Python :: 3.9
Classifier: Programming Language :: Python :: 3.10
Classifier: Programming Language :: Python :: 3.11
Classifier: Programming Language :: Python :: 3.12
Requires-Python: >=3.9
Requires-Dist: WebOb (>=1.7.1)
Requires-Dist: bcrypt (>=3.1.3)
Requires-Dist: oslo.concurrency (>=3.26.0)
Requires-Dist: oslo.config (>=5.2.0)
Requires-Dist: oslo.i18n (>=3.15.3)
Requires-Dist: oslo.utils (>=3.34.0)
Requires-Dist: pbr (>=6.0.0)
Requires-Dist: zeroconf (>=0.24.0)
